src/__init__.py
src/__version__.py
src/basis.py
src/cli.py
src/symm.py
src/symm_util.py
src/write_util.py
symmetry_analysis-0.1.0.dist-info/LICENSE
symmetry_analysis-0.1.0.dist-info/METADATA
symmetry_analysis-0.1.0.dist-info/WHEEL
symmetry_analysis-0.1.0.dist-info/entry_points.txt
symmetry_analysis-0.1.0.dist-info/top_level.txt
symmetry_analysis-0.1.0.dist-info/RECORD
