Metadata-Version: 2.2
Name: symmetry_analysis
Version: 0.1.0
Summary: A programme for analysing molecular (pseudo)-point group symmetry
Author: William Morrillo
Author-email: williammorrillo@gmail.com
Classifier: Programming Language :: Python :: 3
Classifier: License :: OSI Approved :: GNU General Public License v3 (GPLv3)
Classifier: Operating System :: OS Independent
Requires-Python: >=3.6
License-File: LICENSE
Requires-Dist: numpy
Requires-Dist: vasp_suite
Dynamic: author
Dynamic: author-email
Dynamic: classifier
Dynamic: description-content-type
Dynamic: requires-dist
Dynamic: requires-python
Dynamic: summary
